odoo9_addon_openeducat_core-9.0.2.4.0-py2.7-nspkg.pth
odoo_addons/openeducat_core/__openerp__.py
odoo_addons/openeducat_core/__init__.py
odoo_addons/openeducat_core/security/op_security.xml
odoo_addons/openeducat_core/security/ir.model.access.csv
odoo_addons/openeducat_core/report/report_student_idcard.py
odoo_addons/openeducat_core/report/report_student_bonafide.py
odoo_addons/openeducat_core/report/report_student_bonafide.xml
odoo_addons/openeducat_core/report/__init__.py
odoo_addons/openeducat_core/report/report_menu.xml
odoo_addons/openeducat_core/report/report_student_idcard.xml
odoo_addons/openeducat_core/dashboard/faculty_dashboard_view.xml
odoo_addons/openeducat_core/dashboard/student_dashboard_view.xml
odoo_addons/openeducat_core/models/hr.py
odoo_addons/openeducat_core/models/subject.py
odoo_addons/openeducat_core/models/roll_number.py
odoo_addons/openeducat_core/models/course.py
odoo_addons/openeducat_core/models/__init__.py
odoo_addons/openeducat_core/models/student.py
odoo_addons/openeducat_core/models/batch.py
odoo_addons/openeducat_core/models/res_company.py
odoo_addons/openeducat_core/models/faculty.py
odoo_addons/openeducat_core/i18n/openeducat_core.pot
odoo_addons/openeducat_core/wizard/faculty_create_employee_wizard_view.xml
odoo_addons/openeducat_core/wizard/faculty_create_employee_wizard.py
odoo_addons/openeducat_core/wizard/students_create_user_wizard_view.xml
odoo_addons/openeducat_core/wizard/faculty_create_user_wizard.py
odoo_addons/openeducat_core/wizard/__init__.py
odoo_addons/openeducat_core/wizard/students_create_user_wizard.py
odoo_addons/openeducat_core/wizard/faculty_create_user_wizard_view.xml
odoo_addons/openeducat_core/views/openeducat_template.xml
odoo_addons/openeducat_core/views/batch_view.xml
odoo_addons/openeducat_core/views/homepage_template.xml
odoo_addons/openeducat_core/views/student_view.xml
odoo_addons/openeducat_core/views/hr_view.xml
odoo9_addon_openeducat_core-9.0.2.4.0.dist-info/top_level.txt
odoo9_addon_openeducat_core-9.0.2.4.0.dist-info/WHEEL
odoo9_addon_openeducat_core-9.0.2.4.0.dist-info/RECORD
odoo9_addon_openeducat_core-9.0.2.4.0.dist-info/metadata.json
odoo9_addon_openeducat_core-9.0.2.4.0.dist-info/DESCRIPTION.rst
odoo9_addon_openeducat_core-9.0.2.4.0.dist-info/METADATA
odoo9_addon_openeducat_core-9.0.2.4.0.dist-info/namespace_packages.txt
