Metadata-Version: 2.0
Name: odoo9-addon-openeducat-core
Version: 9.0.2.4.0
Summary: Manage Students, Faculties and Education Institute
Home-page: http://www.openeducat.org
Author: UNKNOWN
Author-email: UNKNOWN
License: UNKNOWN
Platform: UNKNOWN
Requires-Dist: odoo (<9.1a,>=9.0a)
Classifier: Programming Language :: Python :: 2.7
Classifier: Framework :: Odoo
